systemdspawner/__init__.py
systemdspawner/systemd.py
systemdspawner/systemdspawner.py
jupyterhub_systemdspawner-1.0.2.dist-info/LICENSE
jupyterhub_systemdspawner-1.0.2.dist-info/METADATA
jupyterhub_systemdspawner-1.0.2.dist-info/WHEEL
jupyterhub_systemdspawner-1.0.2.dist-info/entry_points.txt
jupyterhub_systemdspawner-1.0.2.dist-info/top_level.txt
jupyterhub_systemdspawner-1.0.2.dist-info/RECORD
