Metadata-Version: 2.1
Name: jupyterhub-systemdspawner
Version: 1.0.2
Summary: JupyterHub Spawner using systemd for resource isolation
Home-page: https://github.com/jupyterhub/systemdspawner
Author: Yuvi Panda
Author-email: yuvipanda@gmail.com
License: 3 Clause BSD
Requires-Python: >=3.8
License-File: LICENSE
Requires-Dist: jupyterhub >=2.3.0
Requires-Dist: tornado >=5.1
Provides-Extra: test
Requires-Dist: pytest ; extra == 'test'
Requires-Dist: pytest-asyncio ; extra == 'test'
Requires-Dist: pytest-cov ; extra == 'test'
Requires-Dist: pytest-jupyterhub ; extra == 'test'
